Metadata-Version: 2.1
Name: Droplet-Detector
Version: 0.1.3
Summary: Telegram bot that draws the outlines of drips on a photo !!! Warning!!!  Before running, be sure to create the folders "exel", "new_file" and "save_docs" in the workspace where the python file is located !!!!
Home-page: https://github.com/kvasik3000/Droplet-Detector
Author: Kvas Andrey, Belkova Ksenia, Nekrasova Anna
Author-email: superadrenoline3000@gmail.com
License: Apache License, Version 2.0, see LICENSE file
Platform: UNKNOWN
Classifier: Programming Language :: Python :: 3.9
Classifier: Operating System :: OS Independent
Requires-Python: ==3.9.*
License-File: LICENSE
